mocap_object_detection/__init__.py
mocap_object_detection/axengine_1759765892_3240681702.py
mocap_object_detection/classification/__init__.py
mocap_object_detection/classification/dataset.py
mocap_object_detection/classification/detections.py
mocap_object_detection/classification/detectron_detector.py
mocap_object_detection/classification/net.py
mocap_object_detection/classification/pretrained/log.txt
mocap_object_detection/classification/step_detection_final.py
mocap_object_detection/classification/test_detectron2.py
mocap_object_detection/classification/utils.py
mocap_object_detection/classification/yolo5_detector.py
mocap_object_detection/kalmanMarkers/Data/cup_01_final_03_padding.pkl
mocap_object_detection/kalmanMarkers/__init__.py
mocap_object_detection/kalmanMarkers/cov_matrices.py
mocap_object_detection/kalmanMarkers/feeders.py
mocap_object_detection/kalmanMarkers/interfaces_markers/__init__.py
mocap_object_detection/kalmanMarkers/interfaces_markers/data_feeder.py
mocap_object_detection/kalmanMarkers/interfaces_markers/kalman_interfaces.py
mocap_object_detection/kalmanMarkers/interfaces_markers/prop_interfaces.py
mocap_object_detection/kalmanMarkers/interfaces_markers/smoother.py
mocap_object_detection/kalmanMarkers/kalman.py
mocap_object_detection/kalmanMarkers/main_run_kalman.py
mocap_object_detection/kalmanMarkers/main_run_kalman_local.py
mocap_object_detection/kalmanMarkers/observers.py
mocap_object_detection/kalmanMarkers/props.py
mocap_object_detection/kalmanMarkers/run_kalman.py
mocap_object_detection/kalmanMarkers/smoothers.py
mocap_object_detection/kalmanMarkers/test.py
mocap_object_detection/kalmanMarkers/test_geom.py
mocap_object_detection/kalmanMarkers/ultils/kalman_utils.py
mocap_object_detection/markersTracking/inference_markers_local.py
mocap_object_detection/markersTracking/main_detectors.py
mocap_object_detection/markersTracking/markers_detector.py
mocap_object_detection/markersTracking/models/__init__.py
mocap_object_detection-2.4.0.dist-info/METADATA
mocap_object_detection-2.4.0.dist-info/WHEEL
mocap_object_detection-2.4.0.dist-info/RECORD
