Metadata-Version: 2.1
Name: mocap-object-detection
Version: 2.4.0
Summary: 
Keywords: MotionOps,Moveai
Author: move.ai
Author-email: info@move.ai
Requires-Python: >=3.10,<4.0
Classifier: Programming Language :: Python :: 3
Classifier: Programming Language :: Python :: 3.10
Classifier: Programming Language :: Python :: 3.11
Classifier: Programming Language :: Python :: 3.12
Requires-Dist: mocap-base (>=2.0.1,<3.0.0)
Requires-Dist: mocap_settings (>=1.6.9,<2.0.0)
Requires-Dist: moviepy (>=1.0.3,<2.0.0)
Requires-Dist: scikit-video (>=1.1.11,<2.0.0)
Requires-Dist: torch (==1.13.0)
Requires-Dist: yolov5 (==6.2.0)
